bayeslap/__init__.py
bayeslap/_numpy/__init__.py
bayeslap/_numpy/bayes_error_rbf_kernel.py
bayeslap/_numpy/x_gradient_rbf_kernel.py
bayeslap/_torch/__init__.py
bayeslap/_torch/bayes_error_image_feature_autograd_function.py
bayeslap/_torch/bayes_error_image_feature_autograd_function_efficient.py
bayeslap/_torch/bayes_error_logistic.py
bayeslap/_torch/bayes_error_logistic_autograd_function.py
bayeslap/_torch/bayes_error_logistic_efficient.py
bayeslap/_torch/bayes_error_rbf_kernel.py
bayeslap/_torch/bayes_error_rbf_kernel_autograd_function.py
bayeslap/_torch/x_gradient_autograd.py
bayeslap/_torch/x_gradient_logistic_analytic.py
bayeslap/_torch/x_gradient_logistic_analytic_efficient.py
bayeslap/_torch/x_gradient_rbf_kernel_analytic.py
bayeslap/_torch/x_gradient_rbf_kernel_analytic_efficient.py
bayeslap/_torch/x_gradient_rbf_kernel_analytic_vectorised.py
bayeslap/_torch/x_gradient_rbf_kernel_autograd.py
bayeslap/_torch/x_gradient_rbf_kernel_autograd_efficient.py
bayeslap-0.0.1.dist-info/licenses/LICENSE
bayeslap-0.0.1.dist-info/METADATA
bayeslap-0.0.1.dist-info/WHEEL
bayeslap-0.0.1.dist-info/top_level.txt
bayeslap-0.0.1.dist-info/zip-safe
bayeslap-0.0.1.dist-info/RECORD
